pychelper/__init__.py
pychelper/__main__.py
pychelper-0.1.5.dist-info/LICENSE
pychelper-0.1.5.dist-info/METADATA
pychelper-0.1.5.dist-info/WHEEL
pychelper-0.1.5.dist-info/top_level.txt
pychelper-0.1.5.dist-info/RECORD
