Metadata-Version: 2.1
Name: pychelper
Version: 0.1.5
Summary: Python project compilation helper that compile python files and copy resource files
Home-page: http://theorozier.fr
Author: Théo Rozier
Author-email: contact@theorozier.fr
License: UNKNOWN
Platform: UNKNOWN
Classifier: Programming Language :: Python :: 3
Classifier: License :: OSI Approved :: MIT License
Classifier: Operating System :: OS Independent
Requires-Python: >=3.5
